tinymce/__init__.py
tinymce/compressor.py
tinymce/models.py
tinymce/settings.py
tinymce/urls.py
tinymce/views.py
tinymce/widgets.py
tinymce/static/django_tinymce/init_tinymce.js
tinymce/static/tinymce/license.txt
tinymce/static/tinymce/tinymce.d.ts
tinymce/static/tinymce/tinymce.min.js
tinymce/static/tinymce/icons/default/icons.min.js
tinymce/static/tinymce/langs/README.md
tinymce/static/tinymce/langs/ar.js
tinymce/static/tinymce/langs/ar_SA.js
tinymce/static/tinymce/langs/az.js
tinymce/static/tinymce/langs/be.js
tinymce/static/tinymce/langs/bg_BG.js
tinymce/static/tinymce/langs/bn_BD.js
tinymce/static/tinymce/langs/ca.js
tinymce/static/tinymce/langs/cs.js
tinymce/static/tinymce/langs/cy.js
tinymce/static/tinymce/langs/da.js
tinymce/static/tinymce/langs/de.js
tinymce/static/tinymce/langs/dv.js
tinymce/static/tinymce/langs/el.js
tinymce/static/tinymce/langs/eo.js
tinymce/static/tinymce/langs/es.js
tinymce/static/tinymce/langs/es_MX.js
tinymce/static/tinymce/langs/et.js
tinymce/static/tinymce/langs/eu.js
tinymce/static/tinymce/langs/fa.js
tinymce/static/tinymce/langs/fi.js
tinymce/static/tinymce/langs/fr_FR.js
tinymce/static/tinymce/langs/ga.js
tinymce/static/tinymce/langs/gl.js
tinymce/static/tinymce/langs/he_IL.js
tinymce/static/tinymce/langs/hi.js
tinymce/static/tinymce/langs/hr.js
tinymce/static/tinymce/langs/hu_HU.js
tinymce/static/tinymce/langs/hy.js
tinymce/static/tinymce/langs/id.js
tinymce/static/tinymce/langs/is_IS.js
tinymce/static/tinymce/langs/it.js
tinymce/static/tinymce/langs/ja.js
tinymce/static/tinymce/langs/ka_GE.js
tinymce/static/tinymce/langs/kab.js
tinymce/static/tinymce/langs/kk.js
tinymce/static/tinymce/langs/ko_KR.js
tinymce/static/tinymce/langs/ku.js
tinymce/static/tinymce/langs/lt.js
tinymce/static/tinymce/langs/lv.js
tinymce/static/tinymce/langs/nb_NO.js
tinymce/static/tinymce/langs/ne.js
tinymce/static/tinymce/langs/nl.js
tinymce/static/tinymce/langs/nl_BE.js
tinymce/static/tinymce/langs/oc.js
tinymce/static/tinymce/langs/pl.js
django_tinymce-4.0.0.dist-info/LICENSE.txt
django_tinymce-4.0.0.dist-info/METADATA
django_tinymce-4.0.0.dist-info/WHEEL
django_tinymce-4.0.0.dist-info/top_level.txt
django_tinymce-4.0.0.dist-info/RECORD
