Metadata-Version: 2.1
Name: django-tinymce
Version: 4.0.0
Summary: A Django application that contains a widget to render a
Author-email: Aljosa Mohorovic <aljosa.mohorovic@gmail.com>
Maintainer-email: Rémy Hubscher <hubscher.remy@gmail.com>, Claude Paroz <claude@2xlibre.net>
License: MIT License
Project-URL: Homepage, https://github.com/jazzband/django-tinymce
Project-URL: Documentation, https://django-tinymce.readthedocs.org/
Project-URL: Changelog, https://github.com/jazzband/django-tinymce/blob/master/CHANGELOG.rst
Keywords: django,widget,tinymce
Classifier: Development Status :: 5 - Production/Stable
Classifier: Environment :: Web Environment
Classifier: Framework :: Django
Classifier: Framework :: Django :: 3.2
Classifier: Framework :: Django :: 4.2
Classifier: Framework :: Django :: 5.0
Classifier: Intended Audience :: Developers
Classifier: License :: OSI Approved :: MIT License
Classifier: Operating System :: OS Independent
Classifier: Programming Language :: Python
Classifier: Programming Language :: Python :: 3
Classifier: Programming Language :: Python :: 3.8
Classifier: Programming Language :: Python :: 3.9
Classifier: Programming Language :: Python :: 3.10
Classifier: Programming Language :: Python :: 3.11
Classifier: Programming Language :: Python :: 3.12
Classifier: Topic :: Software Development :: Libraries :: Application Frameworks
Classifier: Topic :: Software Development :: Libraries :: Python Modules
Requires-Python: >=3.8
License-File: LICENSE.txt
Requires-Dist: django>=3.2
